.coveragerc
.gitignore
.isort.cfg
.pre-commit-config.yaml
.readthedocs.yml
AUTHORS.md
CHANGELOG.md
CONTRIBUTING.md
LICENSE.txt
MANIFEST.in
README.md
pyproject.toml
setup.cfg
setup.py
tox.ini
.github/workflows/pypi-test.yml
extern/fetch.py
extern/manifest.csv
src/assorthead/__init__.py
src/assorthead/includes.py
src/assorthead.egg-info/PKG-INFO
src/assorthead.egg-info/SOURCES.txt
src/assorthead.egg-info/dependency_links.txt
src/assorthead.egg-info/not-zip-safe
src/assorthead.egg-info/requires.txt
src/assorthead.egg-info/top_level.txt
src/assorthead/include/Eigen/AccelerateSupport
src/assorthead/include/Eigen/Cholesky
src/assorthead/include/Eigen/CholmodSupport
src/assorthead/include/Eigen/Core
src/assorthead/include/Eigen/Dense
src/assorthead/include/Eigen/Eigen
src/assorthead/include/Eigen/Eigenvalues
src/assorthead/include/Eigen/Geometry
src/assorthead/include/Eigen/Householder
src/assorthead/include/Eigen/IterativeLinearSolvers
src/assorthead/include/Eigen/Jacobi
src/assorthead/include/Eigen/KLUSupport
src/assorthead/include/Eigen/LU
src/assorthead/include/Eigen/MetisSupport
src/assorthead/include/Eigen/OrderingMethods
src/assorthead/include/Eigen/PaStiXSupport
src/assorthead/include/Eigen/PardisoSupport
src/assorthead/include/Eigen/QR
src/assorthead/include/Eigen/QtAlignedMalloc
src/assorthead/include/Eigen/SPQRSupport
src/assorthead/include/Eigen/SVD
src/assorthead/include/Eigen/Sparse
src/assorthead/include/Eigen/SparseCholesky
src/assorthead/include/Eigen/SparseCore
src/assorthead/include/Eigen/SparseLU
src/assorthead/include/Eigen/SparseQR
src/assorthead/include/Eigen/StdDeque
src/assorthead/include/Eigen/StdList
src/assorthead/include/Eigen/StdVector
src/assorthead/include/Eigen/SuperLUSupport
src/assorthead/include/Eigen/ThreadPool
src/assorthead/include/Eigen/UmfPackSupport
src/assorthead/include/Eigen/Version
src/assorthead/include/Eigen/src/AccelerateSupport/AccelerateSupport.h
src/assorthead/include/Eigen/src/AccelerateSupport/InternalHeaderCheck.h
src/assorthead/include/Eigen/src/Cholesky/InternalHeaderCheck.h
src/assorthead/include/Eigen/src/Cholesky/LDLT.h
src/assorthead/include/Eigen/src/Cholesky/LLT.h
src/assorthead/include/Eigen/src/Cholesky/LLT_LAPACKE.h
