Metadata-Version: 2.4
Name: assorthead
Version: 0.2.2
Summary: Assorted C++ headers
Home-page: https://github.com/BiocPy/assorthead/
Author: Aaron Lun
Author-email: infinite.monkeys.with.keyboards@gmail.com
License: MIT
Project-URL: Documentation, https://github.com/BiocPy/assorthead
Project-URL: Tracker, https://github.com/BiocPy/assorthead/issues
Platform: any
Classifier: Development Status :: 4 - Beta
Classifier: Programming Language :: Python
License-File: LICENSE.txt
Requires-Dist: importlib-metadata; python_version < "3.8"
Provides-Extra: testing
Requires-Dist: setuptools; extra == "testing"
Requires-Dist: pytest; extra == "testing"
Requires-Dist: pytest-cov; extra == "testing"
Dynamic: license-file
